labquest/__init__.py
labquest/config.py
labquest/labquest_buffer_functions.py
labquest/labquest_dcu_functions.py
labquest/labquest_init_functions.py
labquest/labquest_open_functions.py
labquest/labquest_photogate_timing_functions.py
labquest/labquest_read_functions.py
labquest/labquest_select_sensors_functions.py
labquest/labquest_sensor_info_functions.py
labquest/labquest_start_functions.py
labquest/labquest_stop_close_functions.py
labquest/ngio_library_functions.py
labquest/ngio_open_functions.py
labquest/ngio_read_functions.py
labquest/ngio_send_cmd_get_resp.py
labquest/ngio_sensor_functions.py
labquest/ngio_start_functions.py
labquest/ngio_stop_functions.py
labquest/data/NGIO_lib_for_32bit_python.dll
labquest/data/NGIO_lib_for_64bit_python.dll
labquest/data/libNGIOUniversal.dylib
labquest/data/resistorsensorlist.txt
labquest-2.1.0.dist-info/licenses/LICENSE
labquest-2.1.0.dist-info/METADATA
labquest-2.1.0.dist-info/WHEEL
labquest-2.1.0.dist-info/top_level.txt
labquest-2.1.0.dist-info/RECORD
