Metadata-Version: 2.4
Name: labquest
Version: 2.1.0
Summary: Library to interface with LabQuest interfaces via USB
Author-email: Vernier Software and Technology <info@vernier.com>
Maintainer-email: Vernier Software and Technology <info@vernier.com>
License-Expression: GPL-3.0
Project-URL: Homepage, https://github.com/vernierst/labquest-py
Project-URL: Repository, https://github.com/vernierst/labquest-py
Keywords: labquest,vernier,usb,interface
Classifier: Programming Language :: Python :: 3
Classifier: Operating System :: MacOS :: MacOS X
Classifier: Operating System :: Microsoft :: Windows
Requires-Python: >=3.7
License-File: LICENSE
Dynamic: license-file
